ISL/Trabalho/parte1/design.sv
// Implementação Comportamental do Flip-Flop tipo D
module DFlipFlop(clk, D, Q);
  input clk, D;
  output reg Q;
  always @(posedge clk)
    begin
      Q = D;
    end
endmodule

// Implementação Estrutural do Flip-Flop tipo D
// utilizando o modelo de Katz (p. 271)
module FlipFlopD(clk, D, Q);
  input clk, D;
  output Q;
  wire nD, nC, R_M, S_M, R_S, S_S, Q_M, Qb_M, Q_S, Qb_S;
  
  not notD(nD, D);
  not notC(nC, clk);
  
  and and_M1(S_M, D, nC);
  and and_M2(R_M, nD, nC);
  Latch_SR Master(Q_M, Qb_M, S_M, R_M);
  
  and and_S1(S_S, Q_M, clk);
  and and_S2(R_S, Qb_M, clk);
  Latch_SR Slave(Q_S, Qb_S, S_S, R_S);
  
  assign Q = Q_S;
  
endmodule

// Latch SR
module Latch_SR(Q, Qbar, S, R);
  input S, R;
  output Q, Qbar;
  
  nor nor1(Q, R, Qbar);
  nor nor2(Qbar, S, Q);
endmodule

ISL/Trabalho/parte1/testbench.sv
// Code your testbench here
// or browse Examples
module testbench;
  reg clk,D;
  wire Q;
  // Modelo Estrutural
  FlipFlopD DFF(clk,D,Q);
  
  // Modelo Comportamental
//   DFlipFlop DFF(clk, D, Q);
  initial
    begin
      clk=0;
      forever #1 clk=~clk;
    end
  initial
    begin
      $dumpfile("dump.vcd");
      $dumpvars(1,testbench);
      $monitor($time," clk = %b,D = %b,Q = %b",clk,D,Q);
      D=0;
      #2 D=1;
      #2 D=0;
      #2 D=1;
      #2 D=0;
      #2 D=0;
      #2 D=1;
      #2 D=0;
      #4 $finish;
    end
  endmodule

ISL/Trabalho/parte1/dump.vcd
$date
	Sat Feb 12 12:50:10 2022
$end
$version
	Icarus Verilog
$end
$timescale
	1s
$end
$scope module testbench $end
$var wire 1 ! Q $end
$var reg 1 " D $end
$var reg 1 # clk $end
$upscope $end
$enddefinitions $end
#0
$dumpvars
0#
0"
x!
$end
#1
0!
1#
#2
0#
1"
#3
1!
1#
#4
0#
0"
#5
0!
1#
#6
0#
1"
#7
1!
1#
#8
0#
0"
#9
0!
1#
#10
0#
#11
1#
#12
0#
1"
#13
1!
1#
#14
0#
0"
#15
0!
1#
