ISL/Trabalho/parte2/design.sv
// Registrador de Deslocamento conforme modelo mostrado 
// no livro Fundamentals of Logic Design, 7ª Edição, pg.382
module ShiftRegister_8bit(data, sh, load, clk, serial_out, parallel_out);
  input [7:0]data;
  input sh;
  input load;
  input clk;
  output serial_out;
  output [7:0]parallel_out;
  
  // Resultado dos multiplexadores
  wire wire_m7;
  wire wire_m6;
  wire wire_m5;
  wire wire_m4;
  wire wire_m3;
  wire wire_m2;
  wire wire_m1;
  wire wire_m0;
  
  // Resultado dos Flip-Flop
  wire wire_dff7;
  wire wire_dff6;
  wire wire_dff5;
  wire wire_dff4;
  wire wire_dff3;
  wire wire_dff2;
  wire wire_dff1;
  wire wire_dff0;
  
  // Instanciando os multiplexadores
  mux_4to1 m7(.in00(wire_dff7), .in01(data[7]), .in10(wire_dff0),
              .in11(wire_dff0), .Sh(sh), .L(load), .out(wire_m7));
  
  mux_4to1 m6(.in00(wire_dff6), .in01(data[6]), .in10(wire_dff7),
              .in11(wire_dff7), .Sh(sh), .L(load), .out(wire_m6));
  
  mux_4to1 m5(.in00(wire_dff5), .in01(data[5]), .in10(wire_dff6),
              .in11(wire_dff6), .Sh(sh), .L(load), .out(wire_m5));
  
  mux_4to1 m4(.in00(wire_dff4), .in01(data[4]), .in10(wire_dff5),
              .in11(wire_dff5), .Sh(sh), .L(load), .out(wire_m4));
  
  mux_4to1 m3(.in00(wire_dff3), .in01(data[3]), .in10(wire_dff4),
              .in11(wire_dff4), .Sh(sh), .L(load), .out(wire_m3));
  
  mux_4to1 m2(.in00(wire_dff2), .in01(data[2]), .in10(wire_dff3),
              .in11(wire_dff3), .Sh(sh), .L(load), .out(wire_m2));
  
  mux_4to1 m1(.in00(wire_dff1), .in01(data[1]), .in10(wire_dff2),
              .in11(wire_dff2), .Sh(sh), .L(load), .out(wire_m1));
  
  mux_4to1 m0(.in00(wire_dff0), .in01(data[0]), .in10(wire_dff1),
              .in11(wire_dff1), .Sh(sh), .L(load), .out(wire_m0));
  
  // Instanciando os 8 Flip-Flops
  FlipFlopD dff7(.clk(clk), .D(wire_m7), .Q(wire_dff7));
  FlipFlopD dff6(.clk(clk), .D(wire_m6), .Q(wire_dff6));
  FlipFlopD dff5(.clk(clk), .D(wire_m5), .Q(wire_dff5));
  FlipFlopD dff4(.clk(clk), .D(wire_m4), .Q(wire_dff4));
  FlipFlopD dff3(.clk(clk), .D(wire_m3), .Q(wire_dff3));
  FlipFlopD dff2(.clk(clk), .D(wire_m2), .Q(wire_dff2));
  FlipFlopD dff1(.clk(clk), .D(wire_m1), .Q(wire_dff1));
  FlipFlopD dff0(.clk(clk), .D(wire_m0), .Q(wire_dff0));
  
  // a saída vai ser o conteúdo do último flip-flop
  assign serial_out = wire_dff0;

  // parallel out
  assign parallel_out[7] = wire_dff7;
  assign parallel_out[6] = wire_dff6;
  assign parallel_out[5] = wire_dff5;
  assign parallel_out[4] = wire_dff4;
  assign parallel_out[3] = wire_dff3;
  assign parallel_out[2] = wire_dff2;
  assign parallel_out[1] = wire_dff1;
  assign parallel_out[0] = wire_dff0;

endmodule

// Multiplexador 4-1
// 4 inputs, 2 sinais de seleção, 1 output
module mux_4to1(in00, in01, in10, in11, Sh, L, out);
  input in00, in01, in10, in11, Sh, L;
  output out;
  
  assign out = ((~Sh & ~L) & in00) | ((~Sh & L) & in01) | ((Sh & ~L) & in10) | ((Sh & L) & in11);
  
endmodule

// Implementação Estrutural do Flip-Flop tipo D
// utilizando o modelo de Katz (p. 271)
module FlipFlopD(clk, D, Q);
  input clk, D;
  output Q;
  wire nD, nC, R_M, S_M, R_S, S_S, Q_M, Qb_M, Q_S, Qb_S;
  
  not notD(nD, D);
  not notC(nC, clk);
  
  and and_M1(S_M, D, nC);
  and and_M2(R_M, nD, nC);
  Latch_SR Master(Q_M, Qb_M, S_M, R_M);
  
  and and_S1(S_S, Q_M, clk);
  and and_S2(R_S, Qb_M, clk);
  Latch_SR Slave(Q_S, Qb_S, S_S, R_S);
  
  assign Q = Q_S;
  
endmodule

// Latch SR
module Latch_SR(Q, Qbar, S, R);
  input S, R;
  output Q, Qbar;
  
  nor nor1(Q, R, Qbar);
  nor nor2(Qbar, S, Q);
endmodule

ISL/Trabalho/parte2/testbench.sv
// testbench
module ShiftRegister_8bit_test;
  reg [287:0]msg; // Mensagem a ser cifrada
  reg [287:0]result; // Resultado da cifragem e decifragem
  
  reg [7:0]otp; // One-Time-Pad
  reg sh_enc;
  reg sh_dec;
  reg load;
  reg clk;
  wire serial_out_enc;
  wire serial_out_dec;
  
  integer i;
  
  // Instanciando o Registrador para cifrar a mensagem
  ShiftRegister_8bit enc(.data(otp), .sh(sh_enc), .load(load), .clk(clk),
                         .serial_out(serial_out_enc));
  
  // Instanciando o Registrador para decifrar a mensagem
  ShiftRegister_8bit dec(.data(otp), .sh(sh_enc), .load(load), .clk(clk),
                         .serial_out(serial_out_dec));

  initial 
    begin
  	  clk = 1'b0;
      forever #10 clk = ~clk;  
   	end

  initial
    begin
      $dumpfile("dump.vcd");
      $dumpvars(1, ShiftRegister_8bit_test);
      // msg <= Universidade Federal de Minas Gerais
      msg <= 288'b010101010110111001101001011101100110010101110010011100110110100101100100011000010110010001100101001000000100011001100101011001000110010101110010011000010110110000100000011001000110010100100000010011010110100101101110011000010111001100100000010001110110010101110010011000010110100101110011;
      otp <= 8'b00101010;
      sh_enc <= 0;
      sh_dec <= 0;
      load <= 1;
      
      #10
      $display("Mensagem Original: %36s", msg);
      $display("One-Time-Pad     : %b", otp);
      $display("\nCifrando...");
      sh_enc <= 1;
      load <= 0;
      
      for (i = 0; i < 288; i = i + 1) begin
        #20
        result[i] <= msg[i] ^ serial_out_enc;
      end
      
      $display("Mensagem Cifrada: %36s", result);
      

      $display("\nDecifrando...");
      sh_dec <= 1;

      for (i = 0; i < 288; i = i + 1) begin
        #20
        result[i] <= result[i] ^ serial_out_dec;
      end
      
      $display("Mensagem Decifrada: %36s", result);
      
      #10
      $finish;
    end 
endmodule

ISL/Trabalho/parte2/dump.vcd
$date
	Sun Feb 13 14:53:43 2022
$end
$version
	Icarus Verilog
$end
$timescale
	1s
$end
$scope module ShiftRegister_8bit_test $end
$var wire 1 ! serial_out_dec $end
$var wire 1 " serial_out_enc $end
$var reg 1 # clk $end
$var integer 32 $ i [31:0] $end
$var reg 1 % load $end
$var reg 288 & msg [287:0] $end
$var reg 8 ' otp [7:0] $end
$var reg 288 ( result [287:0] $end
$var reg 1 ) sh_dec $end
$var reg 1 * sh_enc $end
$upscope $end
$enddefinitions $end
#0
$dumpvars
0*
0)
bx (
b101010 '
b10101010110111001101001011101100110010101110010011100110110100101100100011000010110010001100101001000000100011001100101011001000110010101110010011000010110110000100000011001000110010100100000010011010110100101101110011000010111001100100000010001110110010101110010011000010110100101110011 &
1%
bx $
0#
x"
x!
$end
#10
0%
1*
0"
0!
b0 $
1#
#20
0#
#30
bx1 (
1"
1!
1#
b1 $
#40
0#
#50
bx01 (
0"
0!
1#
b10 $
#60
0#
#70
bx001 (
1"
1!
1#
b11 $
#80
0#
#90
bx1001 (
0"
0!
1#
b100 $
#100
0#
#110
bx11001 (
1"
1!
1#
b101 $
#120
0#
#130
bx011001 (
0"
0!
1#
b110 $
#140
0#
#150
bx1011001 (
1#
b111 $
#160
0#
#170
bx01011001 (
1#
b1000 $
#180
0#
#190
bx101011001 (
1"
1!
1#
b1001 $
#200
0#
#210
bx1101011001 (
0"
0!
1#
b1010 $
#220
0#
#230
bx01101011001 (
1"
1!
1#
b1011 $
#240
0#
#250
bx001101011001 (
0"
0!
1#
b1100 $
#260
0#
#270
bx0001101011001 (
1"
1!
1#
b1101 $
#280
0#
#290
bx00001101011001 (
0"
0!
1#
b1110 $
#300
0#
#310
bx100001101011001 (
1#
b1111 $
#320
0#
#330
bx0100001101011001 (
1#
b10000 $
#340
0#
#350
bx10100001101011001 (
1"
1!
1#
b10001 $
#360
0#
#370
bx110100001101011001 (
0"
0!
1#
b10010 $
#380
0#
#390
bx0110100001101011001 (
1"
1!
1#
b10011 $
#400
0#
#410
bx10110100001101011001 (
0"
0!
1#
b10100 $
#420
0#
#430
bx010110100001101011001 (
1"
1!
1#
b10101 $
#440
0#
#450
bx0010110100001101011001 (
0"
0!
1#
b10110 $
#460
0#
#470
bx10010110100001101011001 (
1#
b10111 $
#480
0#
#490
bx010010110100001101011001 (
1#
b11000 $
#500
0#
#510
bx0010010110100001101011001 (
1"
1!
1#
b11001 $
#520
0#
#530
bx00010010110100001101011001 (
0"
0!
1#
b11010 $
#540
0#
#550
bx000010010110100001101011001 (
1"
1!
1#
b11011 $
#560
0#
#570
bx1000010010110100001101011001 (
0"
0!
1#
b11100 $
#580
0#
#590
bx11000010010110100001101011001 (
1"
1!
1#
b11101 $
#600
0#
#610
bx011000010010110100001101011001 (
0"
0!
1#
b11110 $
#620
0#
#630
bx1011000010010110100001101011001 (
1#
b11111 $
#640
0#
#650
bx01011000010010110100001101011001 (
1#
b100000 $
#660
0#
#670
bx101011000010010110100001101011001 (
1"
1!
1#
b100001 $
#680
0#
#690
bx1101011000010010110100001101011001 (
0"
0!
1#
b100010 $
#700
0#
#710
bx11101011000010010110100001101011001 (
1"
1!
1#
b100011 $
#720
0#
#730
bx111101011000010010110100001101011001 (
0"
0!
1#
b100100 $
#740
0#
#750
bx0111101011000010010110100001101011001 (
1"
1!
1#
b100101 $
#760
0#
#770
bx00111101011000010010110100001101011001 (
0"
0!
1#
b100110 $
#780
0#
#790
bx100111101011000010010110100001101011001 (
1#
b100111 $
#800
0#
#810
bx0100111101011000010010110100001101011001 (
1#
b101000 $
#820
0#
#830
bx10100111101011000010010110100001101011001 (
1"
1!
1#
b101001 $
#840
0#
#850
bx010100111101011000010010110100001101011001 (
0"
0!
1#
b101010 $
#860
0#
#870
bx1010100111101011000010010110100001101011001 (
1"
1!
1#
b101011 $
#880
0#
#890
bx11010100111101011000010010110100001101011001 (
0"
0!
1#
b101100 $
#900
0#
#910
bx011010100111101011000010010110100001101011001 (
1"
1!
1#
b101101 $
#920
0#
#930
bx1011010100111101011000010010110100001101011001 (
0"
0!
1#
b101110 $
#940
0#
#950
bx11011010100111101011000010010110100001101011001 (
1#
b101111 $
#960
0#
#970
bx011011010100111101011000010010110100001101011001 (
1#
b110000 $
#980
0#
#990
bx0011011010100111101011000010010110100001101011001 (
1"
1!
1#
b110001 $
#1000
0#
#1010
bx10011011010100111101011000010010110100001101011001 (
0"
0!
1#
b110010 $
#1020
0#
#1030
bx010011011010100111101011000010010110100001101011001 (
1"
1!
1#
b110011 $
#1040
0#
#1050
bx1010011011010100111101011000010010110100001101011001 (
0"
0!
1#
b110100 $
#1060
0#
#1070
bx01010011011010100111101011000010010110100001101011001 (
1"
1!
1#
b110101 $
#1080
0#
#1090
bx001010011011010100111101011000010010110100001101011001 (
0"
0!
1#
b110110 $
#1100
0#
#1110
bx0001010011011010100111101011000010010110100001101011001 (
1#
b110111 $
#1120
0#
#1130
bx00001010011011010100111101011000010010110100001101011001 (
1#
b111000 $
#1140
0#
#1150
bx100001010011011010100111101011000010010110100001101011001 (
1"
1!
1#
b111001 $
#1160
0#
#1170
bx0100001010011011010100111101011000010010110100001101011001 (
0"
0!
1#
b111010 $
#1180
0#
#1190
bx00100001010011011010100111101011000010010110100001101011001 (
1"
1!
1#
b111011 $
#1200
0#
#1210
bx100100001010011011010100111101011000010010110100001101011001 (
0"
0!
1#
b111100 $
#1220
0#
#1230
bx1100100001010011011010100111101011000010010110100001101011001 (
1"
1!
1#
b111101 $
#1240
0#
#1250
bx01100100001010011011010100111101011000010010110100001101011001 (
0"
0!
1#
b111110 $
#1260
0#
#1270
bx101100100001010011011010100111101011000010010110100001101011001 (
1#
b111111 $
#1280
0#
#1290
bx0101100100001010011011010100111101011000010010110100001101011001 (
1#
b1000000 $
#1300
0#
#1310
bx10101100100001010011011010100111101011000010010110100001101011001 (
1"
1!
1#
b1000001 $
#1320
0#
#1330
bx110101100100001010011011010100111101011000010010110100001101011001 (
0"
0!
1#
b1000010 $
#1340
0#
#1350
bx0110101100100001010011011010100111101011000010010110100001101011001 (
1"
1!
1#
b1000011 $
#1360
0#
#1370
bx10110101100100001010011011010100111101011000010010110100001101011001 (
0"
0!
1#
b1000100 $
#1380
0#
#1390
bx010110101100100001010011011010100111101011000010010110100001101011001 (
1"
1!
1#
b1000101 $
#1400
0#
#1410
bx0010110101100100001010011011010100111101011000010010110100001101011001 (
0"
0!
1#
b1000110 $
#1420
0#
#1430
bx10010110101100100001010011011010100111101011000010010110100001101011001 (
1#
b1000111 $
#1440
0#
#1450
bx010010110101100100001010011011010100111101011000010010110100001101011001 (
1#
b1001000 $
#1460
0#
#1470
bx0010010110101100100001010011011010100111101011000010010110100001101011001 (
1"
1!
1#
b1001001 $
#1480
0#
#1490
bx00010010110101100100001010011011010100111101011000010010110100001101011001 (
0"
0!
1#
b1001010 $
#1500
0#
#1510
bx100010010110101100100001010011011010100111101011000010010110100001101011001 (
1"
1!
1#
b1001011 $
#1520
0#
#1530
bx0100010010110101100100001010011011010100111101011000010010110100001101011001 (
0"
0!
1#
b1001100 $
#1540
0#
#1550
bx00100010010110101100100001010011011010100111101011000010010110100001101011001 (
1"
1!
1#
b1001101 $
#1560
0#
#1570
bx000100010010110101100100001010011011010100111101011000010010110100001101011001 (
0"
0!
1#
b1001110 $
#1580
0#
#1590
bx1000100010010110101100100001010011011010100111101011000010010110100001101011001 (
1#
b1001111 $
#1600
0#
#1610
bx01000100010010110101100100001010011011010100111101011000010010110100001101011001 (
1#
b1010000 $
#1620
0#
#1630
bx101000100010010110101100100001010011011010100111101011000010010110100001101011001 (
1"
1!
1#
b1010001 $
#1640
0#
#1650
bx1101000100010010110101100100001010011011010100111101011000010010110100001101011001 (
0"
0!
1#
b1010010 $
#1660
0#
#1670
bx01101000100010010110101100100001010011011010100111101011000010010110100001101011001 (
1"
1!
1#
b1010011 $
#1680
0#
#1690
bx001101000100010010110101100100001010011011010100111101011000010010110100001101011001 (
0"
0!
1#
b1010100 $
#1700
0#
#1710
bx0001101000100010010110101100100001010011011010100111101011000010010110100001101011001 (
1"
1!
1#
b1010101 $
#1720
0#
#1730
bx00001101000100010010110101100100001010011011010100111101011000010010110100001101011001 (
0"
0!
1#
b1010110 $
#1740
0#
#1750
bx100001101000100010010110101100100001010011011010100111101011000010010110100001101011001 (
1#
b1010111 $
#1760
0#
#1770
bx0100001101000100010010110101100100001010011011010100111101011000010010110100001101011001 (
1#
b1011000 $
#1780
0#
#1790
bx10100001101000100010010110101100100001010011011010100111101011000010010110100001101011001 (
1"
1!
1#
b1011001 $
#1800
0#
#1810
bx110100001101000100010010110101100100001010011011010100111101011000010010110100001101011001 (
0"
0!
1#
b1011010 $
#1820
0#
#1830
bx1110100001101000100010010110101100100001010011011010100111101011000010010110100001101011001 (
1"
1!
1#
b1011011 $
#1840
0#
#1850
bx01110100001101000100010010110101100100001010011011010100111101011000010010110100001101011001 (
0"
0!
1#
b1011100 $
#1860
0#
#1870
bx001110100001101000100010010110101100100001010011011010100111101011000010010110100001101011001 (
1"
1!
1#
b1011101 $
#1880
0#
#1890
bx1001110100001101000100010010110101100100001010011011010100111101011000010010110100001101011001 (
0"
0!
1#
b1011110 $
#1900
0#
#1910
bx11001110100001101000100010010110101100100001010011011010100111101011000010010110100001101011001 (
1#
b1011111 $
#1920
0#
#1930
bx011001110100001101000100010010110101100100001010011011010100111101011000010010110100001101011001 (
1#
b1100000 $
#1940
0#
#1950
bx0011001110100001101000100010010110101100100001010011011010100111101011000010010110100001101011001 (
1"
1!
1#
b1100001 $
#1960
0#
#1970
bx10011001110100001101000100010010110101100100001010011011010100111101011000010010110100001101011001 (
0"
0!
1#
b1100010 $
#1980
0#
#1990
bx010011001110100001101000100010010110101100100001010011011010100111101011000010010110100001101011001 (
1"
1!
1#
b1100011 $
#2000
0#
#2010
bx1010011001110100001101000100010010110101100100001010011011010100111101011000010010110100001101011001 (
0"
0!
1#
b1100100 $
#2020
0#
#2030
bx01010011001110100001101000100010010110101100100001010011011010100111101011000010010110100001101011001 (
1"
1!
1#
b1100101 $
#2040
0#
#2050
bx001010011001110100001101000100010010110101100100001010011011010100111101011000010010110100001101011001 (
0"
0!
1#
b1100110 $
#2060
0#
#2070
bx0001010011001110100001101000100010010110101100100001010011011010100111101011000010010110100001101011001 (
1#
b1100111 $
#2080
0#
#2090
bx00001010011001110100001101000100010010110101100100001010011011010100111101011000010010110100001101011001 (
1#
b1101000 $
#2100
0#
#2110
bx100001010011001110100001101000100010010110101100100001010011011010100111101011000010010110100001101011001 (
1"
1!
1#
b1101001 $
#2120
0#
#2130
bx1100001010011001110100001101000100010010110101100100001010011011010100111101011000010010110100001101011001 (
0"
0!
1#
b1101010 $
#2140
0#
#2150
bx11100001010011001110100001101000100010010110101100100001010011011010100111101011000010010110100001101011001 (
1"
1!
1#
b1101011 $
#2160
0#
#2170
bx111100001010011001110100001101000100010010110101100100001010011011010100111101011000010010110100001101011001 (
0"
0!
1#
b1101100 $
#2180
0#
#2190
bx0111100001010011001110100001101000100010010110101100100001010011011010100111101011000010010110100001101011001 (
1"
1!
1#
b1101101 $
#2200
0#
#2210
bx00111100001010011001110100001101000100010010110101100100001010011011010100111101011000010010110100001101011001 (
0"
0!
1#
b1101110 $
#2220
0#
#2230
bx100111100001010011001110100001101000100010010110101100100001010011011010100111101011000010010110100001101011001 (
1#
b1101111 $
#2240
0#
#2250
bx0100111100001010011001110100001101000100010010110101100100001010011011010100111101011000010010110100001101011001 (
1#
b1110000 $
#2260
0#
#2270
bx00100111100001010011001110100001101000100010010110101100100001010011011010100111101011000010010110100001101011001 (
1"
1!
1#
b1110001 $
#2280
0#
#2290
bx100100111100001010011001110100001101000100010010110101100100001010011011010100111101011000010010110100001101011001 (
0"
0!
1#
b1110010 $
#2300
0#
#2310
bx1100100111100001010011001110100001101000100010010110101100100001010011011010100111101011000010010110100001101011001 (
1"
1!
1#
b1110011 $
#2320
0#
#2330
bx11100100111100001010011001110100001101000100010010110101100100001010011011010100111101011000010010110100001101011001 (
0"
0!
1#
b1110100 $
#2340
0#
#2350
bx011100100111100001010011001110100001101000100010010110101100100001010011011010100111101011000010010110100001101011001 (
1"
1!
1#
b1110101 $
#2360
0#
#2370
bx0011100100111100001010011001110100001101000100010010110101100100001010011011010100111101011000010010110100001101011001 (
0"
0!
1#
b1110110 $
#2380
0#
#2390
bx10011100100111100001010011001110100001101000100010010110101100100001010011011010100111101011000010010110100001101011001 (
1#
b1110111 $
#2400
0#
#2410
bx010011100100111100001010011001110100001101000100010010110101100100001010011011010100111101011000010010110100001101011001 (
1#
b1111000 $
#2420
0#
#2430
bx0010011100100111100001010011001110100001101000100010010110101100100001010011011010100111101011000010010110100001101011001 (
1"
1!
1#
b1111001 $
#2440
0#
#2450
bx10010011100100111100001010011001110100001101000100010010110101100100001010011011010100111101011000010010110100001101011001 (
0"
0!
1#
b1111010 $
#2460
0#
#2470
bx010010011100100111100001010011001110100001101000100010010110101100100001010011011010100111101011000010010110100001101011001 (
1"
1!
1#
b1111011 $
#2480
0#
#2490
bx1010010011100100111100001010011001110100001101000100010010110101100100001010011011010100111101011000010010110100001101011001 (
0"
0!
1#
b1111100 $
#2500
0#
#2510
bx01010010011100100111100001010011001110100001101000100010010110101100100001010011011010100111101011000010010110100001101011001 (
1"
1!
1#
b1111101 $
#2520
0#
#2530
bx001010010011100100111100001010011001110100001101000100010010110101100100001010011011010100111101011000010010110100001101011001 (
0"
0!
1#
b1111110 $
#2540
0#
#2550
bx0001010010011100100111100001010011001110100001101000100010010110101100100001010011011010100111101011000010010110100001101011001 (
1#
b1111111 $
#2560
0#
#2570
bx00001010010011100100111100001010011001110100001101000100010010110101100100001010011011010100111101011000010010110100001101011001 (
1#
b10000000 $
#2580
0#
#2590
bx000001010010011100100111100001010011001110100001101000100010010110101100100001010011011010100111101011000010010110100001101011001 (
1"
1!
1#
b10000001 $
#2600
0#
#2610
bx1000001010010011100100111100001010011001110100001101000100010010110101100100001010011011010100111101011000010010110100001101011001 (
0"
0!
1#
b10000010 $
#2620
0#
#2630
bx11000001010010011100100111100001010011001110100001101000100010010110101100100001010011011010100111101011000010010110100001101011001 (
1"
1!
1#
b10000011 $
#2640
0#
#2650
bx011000001010010011100100111100001010011001110100001101000100010010110101100100001010011011010100111101011000010010110100001101011001 (
0"
0!
1#
b10000100 $
#2660
0#
#2670
bx0011000001010010011100100111100001010011001110100001101000100010010110101100100001010011011010100111101011000010010110100001101011001 (
1"
1!
1#
b10000101 $
#2680
0#
#2690
bx00011000001010010011100100111100001010011001110100001101000100010010110101100100001010011011010100111101011000010010110100001101011001 (
0"
0!
1#
b10000110 $
#2700
0#
#2710
bx100011000001010010011100100111100001010011001110100001101000100010010110101100100001010011011010100111101011000010010110100001101011001 (
1#
b10000111 $
#2720
0#
#2730
bx0100011000001010010011100100111100001010011001110100001101000100010010110101100100001010011011010100111101011000010010110100001101011001 (
1#
b10001000 $
#2740
0#
#2750
bx10100011000001010010011100100111100001010011001110100001101000100010010110101100100001010011011010100111101011000010010110100001101011001 (
1"
1!
1#
b10001001 $
#2760
0#
#2770
bx110100011000001010010011100100111100001010011001110100001101000100010010110101100100001010011011010100111101011000010010110100001101011001 (
0"
0!
1#
b10001010 $
#2780
0#
#2790
bx0110100011000001010010011100100111100001010011001110100001101000100010010110101100100001010011011010100111101011000010010110100001101011001 (
1"
1!
1#
b10001011 $
#2800
0#
#2810
bx10110100011000001010010011100100111100001010011001110100001101000100010010110101100100001010011011010100111101011000010010110100001101011001 (
0"
0!
1#
b10001100 $
#2820
0#
#2830
bx010110100011000001010010011100100111100001010011001110100001101000100010010110101100100001010011011010100111101011000010010110100001101011001 (
1"
1!
1#
b10001101 $
#2840
0#
#2850
bx0010110100011000001010010011100100111100001010011001110100001101000100010010110101100100001010011011010100111101011000010010110100001101011001 (
0"
0!
1#
b10001110 $
#2860
0#
#2870
bx10010110100011000001010010011100100111100001010011001110100001101000100010010110101100100001010011011010100111101011000010010110100001101011001 (
1#
b10001111 $
#2880
0#
#2890
bx010010110100011000001010010011100100111100001010011001110100001101000100010010110101100100001010011011010100111101011000010010110100001101011001 (
1#
b10010000 $
#2900
0#
#2910
bx0010010110100011000001010010011100100111100001010011001110100001101000100010010110101100100001010011011010100111101011000010010110100001101011001 (
1"
1!
1#
b10010001 $
#2920
0#
#2930
bx00010010110100011000001010010011100100111100001010011001110100001101000100010010110101100100001010011011010100111101011000010010110100001101011001 (
0"
0!
1#
b10010010 $
#2940
0#
#2950
bx000010010110100011000001010010011100100111100001010011001110100001101000100010010110101100100001010011011010100111101011000010010110100001101011001 (
1"
1!
1#
b10010011 $
#2960
0#
#2970
bx1000010010110100011000001010010011100100111100001010011001110100001101000100010010110101100100001010011011010100111101011000010010110100001101011001 (
0"
0!
1#
b10010100 $
#2980
0#
#2990
bx11000010010110100011000001010010011100100111100001010011001110100001101000100010010110101100100001010011011010100111101011000010010110100001101011001 (
1"
1!
1#
b10010101 $
#3000
0#
#3010
bx011000010010110100011000001010010011100100111100001010011001110100001101000100010010110101100100001010011011010100111101011000010010110100001101011001 (
0"
0!
1#
b10010110 $
#3020
0#
#3030
bx1011000010010110100011000001010010011100100111100001010011001110100001101000100010010110101100100001010011011010100111101011000010010110100001101011001 (
1#
b10010111 $
#3040
0#
#3050
bx01011000010010110100011000001010010011100100111100001010011001110100001101000100010010110101100100001010011011010100111101011000010010110100001101011001 (
1#
b10011000 $
#3060
0#
#3070
bx101011000010010110100011000001010010011100100111100001010011001110100001101000100010010110101100100001010011011010100111101011000010010110100001101011001 (
1"
1!
1#
b10011001 $
#3080
0#
#3090
bx1101011000010010110100011000001010010011100100111100001010011001110100001101000100010010110101100100001010011011010100111101011000010010110100001101011001 (
0"
0!
1#
b10011010 $
#3100
0#
#3110
bx11101011000010010110100011000001010010011100100111100001010011001110100001101000100010010110101100100001010011011010100111101011000010010110100001101011001 (
1"
1!
1#
b10011011 $
#3120
0#
#3130
bx111101011000010010110100011000001010010011100100111100001010011001110100001101000100010010110101100100001010011011010100111101011000010010110100001101011001 (
0"
0!
1#
b10011100 $
#3140
0#
#3150
bx0111101011000010010110100011000001010010011100100111100001010011001110100001101000100010010110101100100001010011011010100111101011000010010110100001101011001 (
1"
1!
1#
b10011101 $
#3160
0#
#3170
bx00111101011000010010110100011000001010010011100100111100001010011001110100001101000100010010110101100100001010011011010100111101011000010010110100001101011001 (
0"
0!
1#
b10011110 $
#3180
0#
#3190
bx100111101011000010010110100011000001010010011100100111100001010011001110100001101000100010010110101100100001010011011010100111101011000010010110100001101011001 (
1#
b10011111 $
#3200
0#
#3210
bx0100111101011000010010110100011000001010010011100100111100001010011001110100001101000100010010110101100100001010011011010100111101011000010010110100001101011001 (
1#
b10100000 $
#3220
0#
#3230
bx00100111101011000010010110100011000001010010011100100111100001010011001110100001101000100010010110101100100001010011011010100111101011000010010110100001101011001 (
1"
1!
1#
b10100001 $
#3240
0#
#3250
bx100100111101011000010010110100011000001010010011100100111100001010011001110100001101000100010010110101100100001010011011010100111101011000010010110100001101011001 (
0"
0!
1#
b10100010 $
#3260
0#
#3270
bx1100100111101011000010010110100011000001010010011100100111100001010011001110100001101000100010010110101100100001010011011010100111101011000010010110100001101011001 (
1"
1!
1#
b10100011 $
#3280
0#
#3290
bx11100100111101011000010010110100011000001010010011100100111100001010011001110100001101000100010010110101100100001010011011010100111101011000010010110100001101011001 (
0"
0!
1#
b10100100 $
#3300
0#
#3310
bx011100100111101011000010010110100011000001010010011100100111100001010011001110100001101000100010010110101100100001010011011010100111101011000010010110100001101011001 (
1"
1!
1#
b10100101 $
#3320
0#
#3330
bx0011100100111101011000010010110100011000001010010011100100111100001010011001110100001101000100010010110101100100001010011011010100111101011000010010110100001101011001 (
0"
0!
1#
b10100110 $
#3340
0#
#3350
bx10011100100111101011000010010110100011000001010010011100100111100001010011001110100001101000100010010110101100100001010011011010100111101011000010010110100001101011001 (
1#
b10100111 $
#3360
0#
#3370
bx010011100100111101011000010010110100011000001010010011100100111100001010011001110100001101000100010010110101100100001010011011010100111101011000010010110100001101011001 (
1#
b10101000 $
#3380
0#
#3390
bx1010011100100111101011000010010110100011000001010010011100100111100001010011001110100001101000100010010110101100100001010011011010100111101011000010010110100001101011001 (
1"
1!
1#
b10101001 $
#3400
0#
#3410
bx11010011100100111101011000010010110100011000001010010011100100111100001010011001110100001101000100010010110101100100001010011011010100111101011000010010110100001101011001 (
0"
0!
1#
b10101010 $
#3420
0#
#3430
bx111010011100100111101011000010010110100011000001010010011100100111100001010011001110100001101000100010010110101100100001010011011010100111101011000010010110100001101011001 (
1"
1!
1#
b10101011 $
#3440
0#
#3450
bx1111010011100100111101011000010010110100011000001010010011100100111100001010011001110100001101000100010010110101100100001010011011010100111101011000010010110100001101011001 (
0"
0!
1#
b10101100 $
#3460
0#
#3470
bx01111010011100100111101011000010010110100011000001010010011100100111100001010011001110100001101000100010010110101100100001010011011010100111101011000010010110100001101011001 (
1"
1!
1#
b10101101 $
#3480
0#
#3490
bx001111010011100100111101011000010010110100011000001010010011100100111100001010011001110100001101000100010010110101100100001010011011010100111101011000010010110100001101011001 (
0"
0!
1#
b10101110 $
#3500
0#
#3510
bx1001111010011100100111101011000010010110100011000001010010011100100111100001010011001110100001101000100010010110101100100001010011011010100111101011000010010110100001101011001 (
1#
b10101111 $
#3520
0#
#3530
bx01001111010011100100111101011000010010110100011000001010010011100100111100001010011001110100001101000100010010110101100100001010011011010100111101011000010010110100001101011001 (
1#
b10110000 $
#3540
0#
#3550
bx001001111010011100100111101011000010010110100011000001010010011100100111100001010011001110100001101000100010010110101100100001010011011010100111101011000010010110100001101011001 (
1"
1!
1#
b10110001 $
#3560
0#
#3570
bx0001001111010011100100111101011000010010110100011000001010010011100100111100001010011001110100001101000100010010110101100100001010011011010100111101011000010010110100001101011001 (
0"
0!
1#
b10110010 $
#3580
0#
#3590
bx10001001111010011100100111101011000010010110100011000001010010011100100111100001010011001110100001101000100010010110101100100001010011011010100111101011000010010110100001101011001 (
1"
1!
1#
b10110011 $
#3600
0#
#3610
bx110001001111010011100100111101011000010010110100011000001010010011100100111100001010011001110100001101000100010010110101100100001010011011010100111101011000010010110100001101011001 (
0"
0!
1#
b10110100 $
#3620
0#
#3630
bx0110001001111010011100100111101011000010010110100011000001010010011100100111100001010011001110100001101000100010010110101100100001010011011010100111101011000010010110100001101011001 (
1"
1!
1#
b10110101 $
#3640
0#
#3650
bx10110001001111010011100100111101011000010010110100011000001010010011100100111100001010011001110100001101000100010010110101100100001010011011010100111101011000010010110100001101011001 (
0"
0!
1#
b10110110 $
#3660
0#
#3670
bx110110001001111010011100100111101011000010010110100011000001010010011100100111100001010011001110100001101000100010010110101100100001010011011010100111101011000010010110100001101011001 (
1#
b10110111 $
#3680
0#
#3690
bx0110110001001111010011100100111101011000010010110100011000001010010011100100111100001010011001110100001101000100010010110101100100001010011011010100111101011000010010110100001101011001 (
1#
b10111000 $
#3700
0#
#3710
bx00110110001001111010011100100111101011000010010110100011000001010010011100100111100001010011001110100001101000100010010110101100100001010011011010100111101011000010010110100001101011001 (
1"
1!
1#
b10111001 $
#3720
0#
#3730
bx100110110001001111010011100100111101011000010010110100011000001010010011100100111100001010011001110100001101000100010010110101100100001010011011010100111101011000010010110100001101011001 (
0"
0!
1#
b10111010 $
#3740
0#
#3750
bx0100110110001001111010011100100111101011000010010110100011000001010010011100100111100001010011001110100001101000100010010110101100100001010011011010100111101011000010010110100001101011001 (
1"
1!
1#
b10111011 $
#3760
0#
